skirnir/__init__.py
skirnir-0.0.1.dist-info/LICENSE
skirnir-0.0.1.dist-info/WHEEL
skirnir-0.0.1.dist-info/METADATA
skirnir-0.0.1.dist-info/RECORD
